{
  "object_id": 209631,
  "excel_metadata": {
    "Object Number": "36.44.7",
    "Is Highlight": false,
    "Is Timeline Work": false,
    "Is Public Domain": false,
    "Object ID": 209631,
    "Gallery Number": null,
    "Department": "European Sculpture and Decorative Arts",
    "AccessionYear": 1936,
    "Object Name": "Fan",
    "Title": "Fan",
    "Culture": "French or Flemish",
    "Period": null,
    "Dynasty": null,
    "Reign": null,
    "Portfolio": null,
    "Constituent ID": null,
    "Artist Role": null,
    "Artist Prefix": null,
    "Artist Display Name": null,
    "Artist Display Bio": null,
    "Artist Suffix": null,
    "Artist Alpha Sort": null,
    "Artist Nationality": null,
    "Artist Begin Date": null,
    "Artist End Date": null,
    "Artist Gender": null,
    "Artist ULAN URL": null,
    "Artist Wikidata URL": null,
    "Object Date": "first half 18th century",
    "Object Begin Date": 1700,
    "Object End Date": 1750,
    "Medium": "Ivory",
    "Dimensions": "8 3/4 x 15 3/4 in.  (22.2 x 40.0 cm)",
    "Credit Line": "Gift of Mrs. Morris Hawkes, 1936",
    "Geography Type": null,
    "City": null,
    "State": null,
    "County": null,
    "Country": null,
    "Region": null,
    "Subregion": null,
    "Locale": null,
    "Locus": null,
    "Excavation": null,
    "River": null,
    "Classification": "Fans",
    "Rights and Reproduction": null,
    "Link Resource": "http://www.metmuseum.org/art/collection/search/209631",
    "Object Wikidata URL": null,
    "Metadata Date": null,
    "Repository": "Metropolitan Museum of Art, New York, NY",
    "Tags": null,
    "Tags AAT URL": null,
    "Tags Wikidata URL": null
  },
  "api_metadata": {
    "primaryImage": "https://images.metmuseum.org/CRDImages/es/original/DP-41535-001.jpg",
    "additionalImages": [
      "https://images.metmuseum.org/CRDImages/es/original/DP-41535-002.jpg"
    ],
    "constituents": null,
    "measurements": [
      {
        "elementName": "Overall",
        "elementDescription": null,
        "elementMeasurements": {
          "Height": 22.2,
          "Width": 40
        }
      }
    ],
    "tags": null
  }
}