{
  "object_id": 326672,
  "excel_metadata": {
    "Object Number": "1981.448.15",
    "Is Highlight": false,
    "Is Timeline Work": false,
    "Is Public Domain": true,
    "Object ID": 326672,
    "Gallery Number": null,
    "Department": "Ancient Near Eastern Art",
    "AccessionYear": 1981,
    "Object Name": "Pin",
    "Title": "Pin",
    "Culture": "Bactria-Margiana Archaeological Complex",
    "Period": "Bronze Age",
    "Dynasty": null,
    "Reign": null,
    "Portfolio": null,
    "Constituent ID": null,
    "Artist Role": null,
    "Artist Prefix": null,
    "Artist Display Name": null,
    "Artist Display Bio": null,
    "Artist Suffix": null,
    "Artist Alpha Sort": null,
    "Artist Nationality": null,
    "Artist Begin Date": null,
    "Artist End Date": null,
    "Artist Gender": null,
    "Artist ULAN URL": null,
    "Artist Wikidata URL": null,
    "Object Date": "ca. late 3rd–early 2nd millennium BCE",
    "Object Begin Date": -2300,
    "Object End Date": -1700,
    "Medium": "Copper alloy",
    "Dimensions": "7.36 in. (18.69 cm)",
    "Credit Line": "Gift of Steven D. Robinson, 1981",
    "Geography Type": null,
    "City": null,
    "State": null,
    "County": null,
    "Country": null,
    "Region": "Bactria-Margiana",
    "Subregion": null,
    "Locale": null,
    "Locus": null,
    "Excavation": null,
    "River": null,
    "Classification": "Metalwork-Ornaments",
    "Rights and Reproduction": null,
    "Link Resource": "http://www.metmuseum.org/art/collection/search/326672",
    "Object Wikidata URL": null,
    "Metadata Date": null,
    "Repository": "Metropolitan Museum of Art, New York, NY",
    "Tags": null,
    "Tags AAT URL": null,
    "Tags Wikidata URL": null
  },
  "api_metadata": {
    "primaryImage": "https://images.metmuseum.org/CRDImages/an/original/ME1981_448_15.jpg",
    "additionalImages": [],
    "constituents": null,
    "measurements": [
      {
        "elementName": "Overall",
        "elementDescription": null,
        "elementMeasurements": {
          "Height": 18.69
        }
      }
    ],
    "tags": null
  }
}