{
  "object_id": 37832,
  "excel_metadata": {
    "Object Number": "31.128.1",
    "Is Highlight": false,
    "Is Timeline Work": false,
    "Is Public Domain": true,
    "Object ID": 37832,
    "Gallery Number": NaN,
    "Department": "Asian Art",
    "AccessionYear": 1931.0,
    "Object Name": "Painting",
    "Title": NaN,
    "Culture": "Tibet",
    "Period": NaN,
    "Dynasty": NaN,
    "Reign": NaN,
    "Portfolio": NaN,
    "Constituent ID": NaN,
    "Artist Role": NaN,
    "Artist Prefix": NaN,
    "Artist Display Name": NaN,
    "Artist Display Bio": NaN,
    "Artist Suffix": NaN,
    "Artist Alpha Sort": NaN,
    "Artist Nationality": NaN,
    "Artist Begin Date": NaN,
    "Artist End Date": NaN,
    "Artist Gender": NaN,
    "Artist ULAN URL": NaN,
    "Artist Wikidata URL": NaN,
    "Object Date": "18th century",
    "Object Begin Date": 1700,
    "Object End Date": 1799,
    "Medium": "Distemper on cloth",
    "Dimensions": "Framed: 41 1/8 x 23 1/8 in. (104.5 x 58.7 cm)\r\nImage: 26 1/4 x 15 3/4 in. (66.7 x 40 cm)\r\nImage (with inscription): 27 1/4 x 15 3/4 in. (69.2 x 40 cm)",
    "Credit Line": "Gift of Mrs. Robert W. de Forest, 1931",
    "Geography Type": NaN,
    "City": NaN,
    "State": NaN,
    "County": NaN,
    "Country": NaN,
    "Region": NaN,
    "Subregion": NaN,
    "Locale": NaN,
    "Locus": NaN,
    "Excavation": NaN,
    "River": NaN,
    "Classification": "Paintings",
    "Rights and Reproduction": NaN,
    "Link Resource": "http://www.metmuseum.org/art/collection/search/37832",
    "Object Wikidata URL": "https://www.wikidata.org/wiki/Q78916196",
    "Metadata Date": NaN,
    "Repository": "Metropolitan Museum of Art, New York, NY",
    "Tags": "Men|Horses|Deities|Buddhism",
    "Tags AAT URL": "http://vocab.getty.edu/page/aat/300025928|http://vocab.getty.edu/page/aat/300250148|http://vocab.getty.edu/page/aat/300343850|http://vocab.getty.edu/page/aat/300073738",
    "Tags Wikidata URL": "https://www.wikidata.org/wiki/Q8441|https://www.wikidata.org/wiki/Q726|https://www.wikidata.org/wiki/Q178885|https://www.wikidata.org/wiki/Q748"
  },
  "api_metadata": {
    "primaryImage": "https://images.metmuseum.org/CRDImages/as/original/31_128_1_86148.jpg",
    "additionalImages": [],
    "constituents": null,
    "measurements": [
      {
        "elementName": "Framed",
        "elementDescription": null,
        "elementMeasurements": {
          "Height": 104.4577,
          "Width": 58.7376
        }
      },
      {
        "elementName": "Image",
        "elementDescription": "with inscription",
        "elementMeasurements": {
          "Height": 69.2151,
          "Width": 40.0051
        }
      },
      {
        "elementName": "Image",
        "elementDescription": null,
        "elementMeasurements": {
          "Height": 66.6751,
          "Width": 40.0051
        }
      }
    ],
    "tags": [
      {
        "term": "Men",
        "AAT_URL": "http://vocab.getty.edu/page/aat/300025928",
        "Wikidata_URL": "https://www.wikidata.org/wiki/Q8441"
      },
      {
        "term": "Horses",
        "AAT_URL": "http://vocab.getty.edu/page/aat/300250148",
        "Wikidata_URL": "https://www.wikidata.org/wiki/Q726"
      },
      {
        "term": "Buddhism",
        "AAT_URL": "http://vocab.getty.edu/page/aat/300073738",
        "Wikidata_URL": "https://www.wikidata.org/wiki/Q748"
      },
      {
        "term": "Deities",
        "AAT_URL": "http://vocab.getty.edu/page/aat/300343850",
        "Wikidata_URL": "https://www.wikidata.org/wiki/Q178885"
      }
    ]
  }
}