{
  "object_id": 447240,
  "excel_metadata": {
    "Object Number": "20.120.166",
    "Is Highlight": false,
    "Is Timeline Work": false,
    "Is Public Domain": true,
    "Object ID": 447240,
    "Gallery Number": null,
    "Department": "Islamic Art",
    "AccessionYear": 1920,
    "Object Name": "Dish",
    "Title": "Dish",
    "Culture": null,
    "Period": null,
    "Dynasty": null,
    "Reign": null,
    "Portfolio": null,
    "Constituent ID": null,
    "Artist Role": null,
    "Artist Prefix": null,
    "Artist Display Name": null,
    "Artist Display Bio": null,
    "Artist Suffix": null,
    "Artist Alpha Sort": null,
    "Artist Nationality": null,
    "Artist Begin Date": null,
    "Artist End Date": null,
    "Artist Gender": null,
    "Artist ULAN URL": null,
    "Artist Wikidata URL": null,
    "Object Date": "18th–19th century",
    "Object Begin Date": 1700,
    "Object End Date": 1899,
    "Medium": "Stonepaste; glazed",
    "Dimensions": "H. 2 5/8 in. (6.7 cm)_x000D_\nDiam. 12 in. (30.5 cm)_x000D_\nWt. 39.8 oz. (1128.4 g)",
    "Credit Line": "The Grinnell Collection, Bequest of William Milne Grinnell, 1920",
    "Geography Type": "Attributed to",
    "City": null,
    "State": null,
    "County": null,
    "Country": "Iran",
    "Region": null,
    "Subregion": null,
    "Locale": null,
    "Locus": null,
    "Excavation": null,
    "River": null,
    "Classification": "Ceramics",
    "Rights and Reproduction": null,
    "Link Resource": "http://www.metmuseum.org/art/collection/search/447240",
    "Object Wikidata URL": null,
    "Metadata Date": null,
    "Repository": "Metropolitan Museum of Art, New York, NY",
    "Tags": null,
    "Tags AAT URL": null,
    "Tags Wikidata URL": null
  },
  "api_metadata": {
    "primaryImage": "https://images.metmuseum.org/CRDImages/is/original/sf20-120-166a.jpg",
    "additionalImages": [
      "https://images.metmuseum.org/CRDImages/is/original/sf20-120-166b.jpg"
    ],
    "constituents": null,
    "measurements": [
      {
        "elementName": "Overall",
        "elementDescription": null,
        "elementMeasurements": {
          "Diameter": 30.4801,
          "Height": 6.6675,
          "Weight": 1.1284378
        }
      }
    ],
    "tags": null
  }
}