{
  "object_id": 449538,
  "excel_metadata": {
    "Object Number": "39.40.1",
    "Is Highlight": false,
    "Is Timeline Work": false,
    "Is Public Domain": true,
    "Object ID": 449538,
    "Gallery Number": 453,
    "Department": "Islamic Art",
    "AccessionYear": 1939,
    "Object Name": "Handle",
    "Title": "Handle",
    "Culture": null,
    "Period": null,
    "Dynasty": null,
    "Reign": null,
    "Portfolio": null,
    "Constituent ID": null,
    "Artist Role": null,
    "Artist Prefix": null,
    "Artist Display Name": null,
    "Artist Display Bio": null,
    "Artist Suffix": null,
    "Artist Alpha Sort": null,
    "Artist Nationality": null,
    "Artist Begin Date": null,
    "Artist End Date": null,
    "Artist Gender": null,
    "Artist ULAN URL": null,
    "Artist Wikidata URL": null,
    "Object Date": "9th–11th century",
    "Object Begin Date": 800,
    "Object End Date": 1099,
    "Medium": "Bone; carved and incised",
    "Dimensions": "H. 4 13/16 in. (12.3 cm) _x000D_\nW. 11/16 (1.8 cm)_x000D_\nThickness: 3/16 in. (0.5 cm)",
    "Credit Line": "Rogers Fund, 1939",
    "Geography Type": "Excavated in",
    "City": "Nishapur",
    "State": null,
    "County": null,
    "Country": "Iran",
    "Region": null,
    "Subregion": null,
    "Locale": null,
    "Locus": null,
    "Excavation": null,
    "River": null,
    "Classification": "Ivories and Bone",
    "Rights and Reproduction": null,
    "Link Resource": "http://www.metmuseum.org/art/collection/search/449538",
    "Object Wikidata URL": "https://www.wikidata.org/wiki/Q116273232",
    "Metadata Date": null,
    "Repository": "Metropolitan Museum of Art, New York, NY",
    "Tags": null,
    "Tags AAT URL": null,
    "Tags Wikidata URL": null
  },
  "api_metadata": {
    "primaryImage": "https://images.metmuseum.org/CRDImages/is/original/sf39-40-1a.jpg",
    "additionalImages": [
      "https://images.metmuseum.org/CRDImages/is/original/123029.jpg",
      "https://images.metmuseum.org/CRDImages/is/original/sf39-40-1b.jpg"
    ],
    "constituents": null,
    "measurements": [
      {
        "elementName": "Other",
        "elementDescription": null,
        "elementMeasurements": {
          "Height": 12.3,
          "Thickness": 0.5,
          "Width": 1.8
        }
      }
    ],
    "tags": null
  }
}