{
  "object_id": 464647,
  "excel_metadata": {
    "Object Number": "17.190.785",
    "Is Highlight": false,
    "Is Timeline Work": false,
    "Is Public Domain": true,
    "Object ID": 464647,
    "Gallery Number": 304,
    "Department": "Medieval Art",
    "AccessionYear": 1917,
    "Object Name": "Plaque",
    "Title": "Book Cover Plaque with the Crucifixion",
    "Culture": "French",
    "Period": null,
    "Dynasty": null,
    "Reign": null,
    "Portfolio": null,
    "Constituent ID": null,
    "Artist Role": null,
    "Artist Prefix": null,
    "Artist Display Name": null,
    "Artist Display Bio": null,
    "Artist Suffix": null,
    "Artist Alpha Sort": null,
    "Artist Nationality": null,
    "Artist Begin Date": null,
    "Artist End Date": null,
    "Artist Gender": null,
    "Artist ULAN URL": null,
    "Artist Wikidata URL": null,
    "Object Date": "ca. 1190–1200",
    "Object Begin Date": 1190,
    "Object End Date": 1200,
    "Medium": "Copper: repoussé, engraved, chased, and gilt, Champlevé enamel",
    "Dimensions": "Overall: 9 1/4 x 4 1/4 x 5/16 in. (23.5 x 10.8 x 0.8 cm)",
    "Credit Line": "Gift of J. Pierpont Morgan, 1917",
    "Geography Type": "Made in",
    "City": "Limoges",
    "State": null,
    "County": null,
    "Country": "France",
    "Region": null,
    "Subregion": null,
    "Locale": null,
    "Locus": null,
    "Excavation": null,
    "River": null,
    "Classification": "Enamels-Champlevé",
    "Rights and Reproduction": null,
    "Link Resource": "http://www.metmuseum.org/art/collection/search/464647",
    "Object Wikidata URL": "https://www.wikidata.org/wiki/Q116252929",
    "Metadata Date": null,
    "Repository": "Metropolitan Museum of Art, New York, NY",
    "Tags": "Saint John|Angels|Christ|Virgin Mary",
    "Tags AAT URL": " |http://vocab.getty.edu/page/aat/300379004|http://vocab.getty.edu/page/ia/901000087|http://vocab.getty.edu/page/ia/901000032",
    "Tags Wikidata URL": " |https://www.wikidata.org/wiki/Q235113|https://www.wikidata.org/wiki/Q642420|https://www.wikidata.org/wiki/Q345"
  },
  "api_metadata": {
    "primaryImage": "https://images.metmuseum.org/CRDImages/md/original/DP315588.jpg",
    "additionalImages": [
      "https://images.metmuseum.org/CRDImages/md/original/sf17-190-785s1.jpg",
      "https://images.metmuseum.org/CRDImages/md/original/sf17-190-785s2.jpg"
    ],
    "constituents": null,
    "measurements": [
      {
        "elementName": "Overall",
        "elementDescription": null,
        "elementMeasurements": {
          "Depth": 0.8,
          "Height": 23.5,
          "Width": 10.8
        }
      }
    ],
    "tags": [
      {
        "term": "Angels",
        "AAT_URL": "http://vocab.getty.edu/page/aat/300379004",
        "Wikidata_URL": "https://www.wikidata.org/wiki/Q235113"
      },
      {
        "term": "Christ",
        "AAT_URL": "http://vocab.getty.edu/page/ia/901000087",
        "Wikidata_URL": "https://www.wikidata.org/wiki/Q642420"
      },
      {
        "term": "Virgin Mary",
        "AAT_URL": "http://vocab.getty.edu/page/ia/901000032",
        "Wikidata_URL": "https://www.wikidata.org/wiki/Q345"
      },
      {
        "term": "Saint John",
        "AAT_URL": null,
        "Wikidata_URL": null
      }
    ]
  }
}