{
  "object_id": 468273,
  "excel_metadata": {
    "Object Number": "49.101.8",
    "Is Highlight": false,
    "Is Timeline Work": false,
    "Is Public Domain": true,
    "Object ID": 468273,
    "Gallery Number": null,
    "Department": "Medieval Art",
    "AccessionYear": 1949,
    "Object Name": "Window leading",
    "Title": "Leading for Stained Glass window with Flagellation (?) Scene",
    "Culture": "French",
    "Period": null,
    "Dynasty": null,
    "Reign": null,
    "Portfolio": null,
    "Constituent ID": null,
    "Artist Role": null,
    "Artist Prefix": null,
    "Artist Display Name": null,
    "Artist Display Bio": null,
    "Artist Suffix": null,
    "Artist Alpha Sort": null,
    "Artist Nationality": null,
    "Artist Begin Date": null,
    "Artist End Date": null,
    "Artist Gender": null,
    "Artist ULAN URL": null,
    "Artist Wikidata URL": null,
    "Object Date": "13th century",
    "Object Begin Date": 1200,
    "Object End Date": 1299,
    "Medium": "Lead",
    "Dimensions": "Overall: 24 1/4 x 24 1/4 in. (61.6 x 61.6 cm)",
    "Credit Line": "Anonymous Gift, 1949",
    "Geography Type": null,
    "City": null,
    "State": null,
    "County": null,
    "Country": null,
    "Region": null,
    "Subregion": null,
    "Locale": null,
    "Locus": null,
    "Excavation": null,
    "River": null,
    "Classification": "Metalwork-Lead",
    "Rights and Reproduction": null,
    "Link Resource": "http://www.metmuseum.org/art/collection/search/468273",
    "Object Wikidata URL": null,
    "Metadata Date": null,
    "Repository": "Metropolitan Museum of Art, New York, NY",
    "Tags": null,
    "Tags AAT URL": null,
    "Tags Wikidata URL": null
  },
  "api_metadata": {
    "primaryImage": "https://images.metmuseum.org/CRDImages/md/original/cdi49-101-8.jpg",
    "additionalImages": [],
    "constituents": null,
    "measurements": [
      {
        "elementName": "Overall",
        "elementDescription": null,
        "elementMeasurements": {
          "Height": 61.5951,
          "Width": 61.5951
        }
      }
    ],
    "tags": null
  }
}