{
  "object_id": 472310,
  "excel_metadata": {
    "Object Number": "25.120.221",
    "Is Highlight": false,
    "Is Timeline Work": false,
    "Is Public Domain": true,
    "Object ID": 472310,
    "Gallery Number": 2,
    "Department": "The Cloisters",
    "AccessionYear": 1925,
    "Object Name": "Sculpture",
    "Title": "Torso of Christ",
    "Culture": "French",
    "Period": null,
    "Dynasty": null,
    "Reign": null,
    "Portfolio": null,
    "Constituent ID": null,
    "Artist Role": null,
    "Artist Prefix": null,
    "Artist Display Name": null,
    "Artist Display Bio": null,
    "Artist Suffix": null,
    "Artist Alpha Sort": null,
    "Artist Nationality": null,
    "Artist Begin Date": null,
    "Artist End Date": null,
    "Artist Gender": null,
    "Artist ULAN URL": null,
    "Artist Wikidata URL": null,
    "Object Date": "late 12th century",
    "Object Begin Date": 1150,
    "Object End Date": 1199,
    "Medium": "Poplar, gesso, paint, and metal leaf",
    "Dimensions": "43 x 13 3/4 x 9 1/2 in. (109.2 x 34.9 x 24.1 cm)",
    "Credit Line": "The Cloisters Collection, 1925",
    "Geography Type": "Made in",
    "City": null,
    "State": null,
    "County": "Auvergne",
    "Country": "France",
    "Region": null,
    "Subregion": null,
    "Locale": null,
    "Locus": null,
    "Excavation": null,
    "River": null,
    "Classification": "Sculpture-Wood",
    "Rights and Reproduction": null,
    "Link Resource": "http://www.metmuseum.org/art/collection/search/472310",
    "Object Wikidata URL": "https://www.wikidata.org/wiki/Q20201086",
    "Metadata Date": null,
    "Repository": "Metropolitan Museum of Art, New York, NY",
    "Tags": "Christ",
    "Tags AAT URL": "http://vocab.getty.edu/page/ia/901000087",
    "Tags Wikidata URL": "https://www.wikidata.org/wiki/Q642420"
  },
  "api_metadata": {
    "primaryImage": "https://images.metmuseum.org/CRDImages/cl/original/DP216430.jpg",
    "additionalImages": [
      "https://images.metmuseum.org/CRDImages/cl/original/DP216428.jpg",
      "https://images.metmuseum.org/CRDImages/cl/original/DP216429.jpg"
    ],
    "constituents": null,
    "measurements": [
      {
        "elementName": "Overall",
        "elementDescription": null,
        "elementMeasurements": {
          "Depth": 24.1,
          "Height": 109.2202,
          "Width": 34.9
        }
      }
    ],
    "tags": [
      {
        "term": "Christ",
        "AAT_URL": "http://vocab.getty.edu/page/ia/901000087",
        "Wikidata_URL": "https://www.wikidata.org/wiki/Q642420"
      }
    ]
  }
}