{
  "object_id": 544504,
  "excel_metadata": {
    "Object Number": "11.215.454",
    "Is Highlight": false,
    "Is Timeline Work": false,
    "Is Public Domain": true,
    "Object ID": 544504,
    "Gallery Number": 119.0,
    "Department": "Egyptian Art",
    "AccessionYear": 1911.0,
    "Object Name": "Painting on mud plaster",
    "Title": "Bench End-Panel from a shelf support in the Palace of Amenhotep III-Fruit Stand",
    "Culture": NaN,
    "Period": "New Kingdom",
    "Dynasty": "Dynasty 18",
    "Reign": "reign of Amenhotep III",
    "Portfolio": NaN,
    "Constituent ID": NaN,
    "Artist Role": NaN,
    "Artist Prefix": NaN,
    "Artist Display Name": NaN,
    "Artist Display Bio": NaN,
    "Artist Suffix": NaN,
    "Artist Alpha Sort": NaN,
    "Artist Nationality": NaN,
    "Artist Begin Date": NaN,
    "Artist End Date": NaN,
    "Artist Gender": NaN,
    "Artist ULAN URL": NaN,
    "Artist Wikidata URL": NaN,
    "Object Date": "ca. 1390–1352 B.C.",
    "Object Begin Date": -1390,
    "Object End Date": -1352,
    "Medium": "Mud plaster, paint",
    "Dimensions": "Unframed: H. 48.9 × W. 34 cm (19 1/4 × 13 3/8 in.); Framed: H. 52 × W. 36 × 7.5 cm, 20.8 kg (20 1/2 × 14 3/16 × 2 15/16 in., 45.8 lb.)",
    "Credit Line": "Rogers Fund, 1911",
    "Geography Type": "From",
    "City": NaN,
    "State": NaN,
    "County": NaN,
    "Country": "Egypt",
    "Region": "Upper Egypt, Thebes",
    "Subregion": "Malqata",
    "Locale": "Palace of Amenhotep III",
    "Locus": "Women's quarters",
    "Excavation": "MMA excavations, 1910–11",
    "River": NaN,
    "Classification": NaN,
    "Rights and Reproduction": NaN,
    "Link Resource": "http://www.metmuseum.org/art/collection/search/544504",
    "Object Wikidata URL": "https://www.wikidata.org/wiki/Q116247692",
    "Metadata Date": NaN,
    "Repository": "Metropolitan Museum of Art, New York, NY",
    "Tags": "Fruit",
    "Tags AAT URL": "http://vocab.getty.edu/page/aat/300011868",
    "Tags Wikidata URL": "https://www.wikidata.org/wiki/Q1364"
  },
  "api_metadata": {
    "primaryImage": "https://images.metmuseum.org/CRDImages/eg/original/11.215.454.jpg",
    "additionalImages": [],
    "constituents": null,
    "measurements": [
      {
        "elementName": "Overall",
        "elementDescription": "Unframed",
        "elementMeasurements": {
          "Height": 48.9,
          "Width": 34
        }
      },
      {
        "elementName": "Overall",
        "elementDescription": "Framed",
        "elementMeasurements": {
          "Depth": 7.5,
          "Height": 52,
          "Weight": 20.774744,
          "Width": 36
        }
      }
    ],
    "tags": [
      {
        "term": "Fruit",
        "AAT_URL": "http://vocab.getty.edu/page/aat/300011868",
        "Wikidata_URL": "https://www.wikidata.org/wiki/Q1364"
      }
    ]
  }
}