{
  "object_id": 749164,
  "excel_metadata": {
    "Object Number": "2020.288.4",
    "Is Highlight": false,
    "Is Timeline Work": false,
    "Is Public Domain": true,
    "Object ID": 749164,
    "Gallery Number": null,
    "Department": "Asian Art",
    "AccessionYear": 2020,
    "Object Name": "Ewer",
    "Title": null,
    "Culture": "Nepal, Bhaktapur",
    "Period": null,
    "Dynasty": null,
    "Reign": null,
    "Portfolio": null,
    "Constituent ID": null,
    "Artist Role": null,
    "Artist Prefix": null,
    "Artist Display Name": null,
    "Artist Display Bio": null,
    "Artist Suffix": null,
    "Artist Alpha Sort": null,
    "Artist Nationality": null,
    "Artist Begin Date": null,
    "Artist End Date": null,
    "Artist Gender": null,
    "Artist ULAN URL": null,
    "Artist Wikidata URL": null,
    "Object Date": "Dated by inscription 1733",
    "Object Begin Date": 1733,
    "Object End Date": 1733,
    "Medium": "Copper alloy",
    "Dimensions": "H. 9 7/16 in. (24 cm); W. to spout 8 7/16 in. (21.5 cm); Diam. of collar 5 1/8 in. (13 cm)",
    "Credit Line": "Zimmerman Family Collection, Gift of the Zimmerman Family, 2020",
    "Geography Type": null,
    "City": null,
    "State": null,
    "County": null,
    "Country": null,
    "Region": null,
    "Subregion": null,
    "Locale": null,
    "Locus": null,
    "Excavation": null,
    "River": null,
    "Classification": "Sculpture",
    "Rights and Reproduction": null,
    "Link Resource": "http://www.metmuseum.org/art/collection/search/749164",
    "Object Wikidata URL": null,
    "Metadata Date": null,
    "Repository": "Metropolitan Museum of Art, New York, NY",
    "Tags": null,
    "Tags AAT URL": null,
    "Tags Wikidata URL": null
  },
  "api_metadata": {
    "primaryImage": "https://images.metmuseum.org/CRDImages/as/original/DP-14528-034.jpg",
    "additionalImages": [
      "https://images.metmuseum.org/CRDImages/as/original/DP-14528-035.jpg",
      "https://images.metmuseum.org/CRDImages/as/original/DP-14528-033.jpg"
    ],
    "constituents": null,
    "measurements": [
      {
        "elementName": "Overall",
        "elementDescription": null,
        "elementMeasurements": {
          "Diameter": 13,
          "Height": 24,
          "Weight": 2.267985,
          "Width": 21.5
        }
      }
    ],
    "tags": null
  }
}