{
  "object_id": 821118,
  "excel_metadata": {
    "Object Number": "55.43.2",
    "Is Highlight": false,
    "Is Timeline Work": false,
    "Is Public Domain": true,
    "Object ID": 821118,
    "Gallery Number": null,
    "Department": "European Sculpture and Decorative Arts",
    "AccessionYear": 1955,
    "Object Name": "Pier glass mirror",
    "Title": "Pier glass mirror (one of a pair)",
    "Culture": "British",
    "Period": null,
    "Dynasty": null,
    "Reign": null,
    "Portfolio": null,
    "Constituent ID": null,
    "Artist Role": null,
    "Artist Prefix": null,
    "Artist Display Name": null,
    "Artist Display Bio": null,
    "Artist Suffix": null,
    "Artist Alpha Sort": null,
    "Artist Nationality": null,
    "Artist Begin Date": null,
    "Artist End Date": null,
    "Artist Gender": null,
    "Artist ULAN URL": null,
    "Artist Wikidata URL": null,
    "Object Date": "ca. 1760",
    "Object Begin Date": 1755,
    "Object End Date": 1765,
    "Medium": "Carved and gilt linden wood, glass",
    "Dimensions": ".2: 9 ft. 7 in. × 55 in. (292.1 × 139.7 cm)",
    "Credit Line": "Purchase, Morris Loeb Bequest, 1955",
    "Geography Type": null,
    "City": null,
    "State": null,
    "County": null,
    "Country": null,
    "Region": null,
    "Subregion": null,
    "Locale": null,
    "Locus": null,
    "Excavation": null,
    "River": null,
    "Classification": "Woodwork-Furniture",
    "Rights and Reproduction": null,
    "Link Resource": "http://www.metmuseum.org/art/collection/search/821118",
    "Object Wikidata URL": null,
    "Metadata Date": null,
    "Repository": "Metropolitan Museum of Art, New York, NY",
    "Tags": "Mirrors|Chinoiserie",
    "Tags AAT URL": "http://vocab.getty.edu/page/aat/300037682|http://vocab.getty.edu/page/aat/300021167",
    "Tags Wikidata URL": "https://www.wikidata.org/wiki/Q35197|https://www.wikidata.org/wiki/Q863679"
  },
  "api_metadata": {
    "primaryImage": "https://images.metmuseum.org/CRDImages/es/original/158968.jpg",
    "additionalImages": [],
    "constituents": null,
    "measurements": [
      {
        "elementName": "Overall",
        "elementDescription": ".2",
        "elementMeasurements": {
          "Height": 292.1006,
          "Width": 139.70029
        }
      }
    ],
    "tags": [
      {
        "term": "Chinoiserie",
        "AAT_URL": "http://vocab.getty.edu/page/aat/300021167",
        "Wikidata_URL": "https://www.wikidata.org/wiki/Q863679"
      }
    ]
  }
}